odoo8_addon_purchase_transport_multi_address-8.0.1.0.0-py2.7-nspkg.pth
odoo8_addon_purchase_transport_multi_address-8.0.1.0.0.dist-info/top_level.txt
odoo8_addon_purchase_transport_multi_address-8.0.1.0.0.dist-info/WHEEL
odoo8_addon_purchase_transport_multi_address-8.0.1.0.0.dist-info/RECORD
odoo8_addon_purchase_transport_multi_address-8.0.1.0.0.dist-info/metadata.json
odoo8_addon_purchase_transport_multi_address-8.0.1.0.0.dist-info/DESCRIPTION.rst
odoo8_addon_purchase_transport_multi_address-8.0.1.0.0.dist-info/METADATA
odoo8_addon_purchase_transport_multi_address-8.0.1.0.0.dist-info/namespace_packages.txt
odoo_addons/purchase_transport_multi_address/__openerp__.py
odoo_addons/purchase_transport_multi_address/__init__.py
odoo_addons/purchase_transport_multi_address/README.rst
odoo_addons/purchase_transport_multi_address/view/purchase.xml
odoo_addons/purchase_transport_multi_address/i18n/purchase_transport_multi_address.pot
odoo_addons/purchase_transport_multi_address/i18n/es.po
odoo_addons/purchase_transport_multi_address/model/purchase_order.py
odoo_addons/purchase_transport_multi_address/model/__init__.py
odoo_addons/purchase_transport_multi_address/model/procurement_order.py
odoo_addons/purchase_transport_multi_address/test/setup_user.yml
odoo_addons/purchase_transport_multi_address/test/setup_product.yml
odoo_addons/purchase_transport_multi_address/test/setup_dropshipping.xml
odoo_addons/purchase_transport_multi_address/test/test_propagate_address.yml
odoo_addons/purchase_transport_multi_address/tests/test_addresses.py
odoo_addons/purchase_transport_multi_address/tests/test_consignee_purchase_order.py
odoo_addons/purchase_transport_multi_address/tests/__init__.py
odoo_addons/purchase_transport_multi_address/static/description/icon.png
